nerdyversary/__init__.py
nerdyversary/__main__.py
nerdyversary/_version.py
nerdyversary-0.1.1.dist-info/LICENSE
nerdyversary-0.1.1.dist-info/METADATA
nerdyversary-0.1.1.dist-info/WHEEL
nerdyversary-0.1.1.dist-info/entry_points.txt
nerdyversary-0.1.1.dist-info/top_level.txt
nerdyversary-0.1.1.dist-info/RECORD
