Metadata-Version: 2.1
Name: nerdyversary
Version: 0.1.1
Summary: Package for computing nerdy anniversaries
Author-email: Roman Ludwig <roman.ludwig@usz.ch>
License: MIT
Project-URL: source, https://github.com/rmnldwg/anniversary
Project-URL: docs, https://rmnldwg.github.io/nerdyversary
Keywords: maths,anniversary,nerdy,irrational-numbers
Classifier: Programming Language :: Python :: 3
Requires-Python: >=3.10
License-File: LICENSE
Requires-Dist: numpy
Requires-Dist: sympy
Requires-Dist: tabulate
Provides-Extra: dev
Requires-Dist: pre-commit ; extra == 'dev'
Requires-Dist: isort ; extra == 'dev'
Requires-Dist: pycln ; extra == 'dev'
Requires-Dist: pylint ; extra == 'dev'
Provides-Extra: docs
Requires-Dist: pdoc ; extra == 'docs'
Provides-Extra: tests
Requires-Dist: pytest ; extra == 'tests'
